antakia_core/__init__.py
antakia_core/compute/__init__.py
antakia_core/compute/dim_reduction/__init__.py
antakia_core/compute/dim_reduction/dim_reduc_method.py
antakia_core/compute/dim_reduction/dim_reduction.py
antakia_core/compute/dim_reduction/pacmap_progress/__init__.py
antakia_core/compute/dim_reduction/pacmap_progress/pacmap_progress.py
antakia_core/compute/model_subtitution/__init__.py
antakia_core/compute/model_subtitution/classification_models.py
antakia_core/compute/model_subtitution/model_class.py
antakia_core/compute/model_subtitution/model_interface.py
antakia_core/compute/model_subtitution/regression_models.py
antakia_core/compute/skope_rule/skope_rule.py
antakia_core/data_handler/__init__.py
antakia_core/data_handler/projected_values.py
antakia_core/data_handler/region.py
antakia_core/data_handler/region_.py
antakia_core/data_handler/region_set.py
antakia_core/data_handler/rule.py
antakia_core/data_handler/rules.py
antakia_core/explanation/__init__.py
antakia_core/explanation/explanation_method.py
antakia_core/explanation/explanations.py
antakia_core/utils/__init__.py
antakia_core/utils/correlation_coef.py
antakia_core/utils/long_task.py
antakia_core/utils/splittable_callback.py
antakia_core/utils/utils.py
antakia_core/utils/variable.py
antakia_core-0.4.6.dist-info/LICENSE
antakia_core-0.4.6.dist-info/METADATA
antakia_core-0.4.6.dist-info/WHEEL
antakia_core-0.4.6.dist-info/RECORD
