Metadata-Version: 2.1
Name: antakia-core
Version: 0.4.6
Summary: Core modules for AntakIA
Author: Pierre Hulot
Author-email: pierre@ai-vidence.com
Requires-Python: >=3.10,<3.13
Classifier: Programming Language :: Python :: 3
Classifier: Programming Language :: Python :: 3.10
Classifier: Programming Language :: Python :: 3.11
Classifier: Programming Language :: Python :: 3.12
Requires-Dist: interpret
Requires-Dist: lime (>=0.2.0.1,<0.3.0.0)
Requires-Dist: pacmap
Requires-Dist: pandas (>=2.2.0,<3.0.0)
Requires-Dist: pygam (<0.9.0) ; python_version < "3.11"
Requires-Dist: pygam (>=0.9.0) ; python_version >= "3.11" and python_version < "3.13"
Requires-Dist: scikit-learn (>=1.4.1.post1,<2.0.0)
Requires-Dist: scipy
Requires-Dist: shap (>=0.43.0,<0.44.0)
Requires-Dist: skope-rules-temp (>=0.2.4)
Requires-Dist: umap-learn (>=0.5.5,<0.6.0)
